{
  "name": "FoundryVTTNaheulbeuk",
  "title": "System de Naheulbeuk modifie",
  "description": "A minimalist game system which provides configurable Actor and Item templates to support free-form system agnostic game-play.",
  "version": "0.6.5",
  "minimumCoreVersion": "0.8.9",
  "compatibleCoreVersion": "9",
  "author": "Abeillle",
  "esmodules": ["module/simple.js"],
  "styles": ["styles/simple.css"],
  "packs": [],
  "languages": [
    {
      "lang": "en",
      "name": "English",
      "path": "lang/en.json"
    }
  ],
  "gridDistance": 5,
  "gridUnits": "m",
  "primaryTokenAttribute": "health",
  "secondaryTokenAttribute": "power",
  "url": "https://github.com/ausecour/FoundryVTTNaheulbeuk/",
  "manifest": "https://github.com/ausecour/FoundryVTTNaheulbeuk/blob/test/system.json",
  "download": "https://github.com/ausecour/FoundryVTTNaheulbeuk/releases/download/test/FoundryVTTNaheulbeuk.zip"
  "license": "LICENSE.txt"
}

